Metadata-Version: 2.1
Name: openaihub-install
Version: 0.0.2
Summary: OpenAIHub installer and others
Home-page: https://github.ibm.com/OpenAIHub/OpenAIHub
Author: Adrian Zhuang
Author-email: wzhuang@us.ibm.com
License: UNKNOWN
Platform: UNKNOWN
Classifier: Programming Language :: Python :: 3
Classifier: License :: OSI Approved :: MIT License
Classifier: Operating System :: OS Independent
